fbref2pandas/__init__.py
fbref2pandas/classes.py
fbref2pandas-0.0.1.dist-info/METADATA
fbref2pandas-0.0.1.dist-info/WHEEL
fbref2pandas-0.0.1.dist-info/licenses/LICENSE
fbref2pandas-0.0.1.dist-info/RECORD
