Metadata-Version: 2.1
Name: fbref2pandas
Version: 0.0.1
Summary: A scraper that directly gives football(not soccer) data from FBRef website directly to Pandas dataframe. Major teams and leagues supported.
Project-URL: Homepage, https://github.com/yash-srivastava19/fbref2pandas
Project-URL: Bug Tracker, https://github.com/yash-srivastava19/fbref2pandas/issues
Author-email: Yash Srivastava <ysrivastava82@gmail.com>
License-File: LICENSE
Classifier: License :: OSI Approved :: MIT License
Classifier: Operating System :: OS Independent
Classifier: Programming Language :: Python :: 3
Requires-Python: >=3.7
